gittask/GitTask.py
gittask/__init__.py
gittask-0.1.1.dist-info/LICENSE
gittask-0.1.1.dist-info/METADATA
gittask-0.1.1.dist-info/WHEEL
gittask-0.1.1.dist-info/entry_points.txt
gittask-0.1.1.dist-info/top_level.txt
gittask-0.1.1.dist-info/RECORD
