Metadata-Version: 2.1
Name: gittask
Version: 0.1.1
Summary: Git-task
Home-page: https://github.com/bessbd/gittask
Author: bessbd
Author-email: bessbd@gmail.com
License: UNKNOWN
Platform: UNKNOWN
Classifier: License :: OSI Approved :: MIT License
Classifier: Operating System :: OS Independent
Requires-Dist: fire
Requires-Dist: pyyaml
